{
  "img": {
    "random": {
      "src": "../../images/img-random-1.png",
      "alt": "A placeholder image with an arbitrary aspect ratio."
    },
    "square": {
      "src": "../../images/img-1x1.png",
      "alt": "A placeholder image with a perfect square (1:1) aspect ratio."
    },
    "tv": {
      "src": "../../images/img-4x3.png",
      "alt": "A placeholder image with a 4:3 aspect ratio, like an old TV."
    },
    "widescreen": {
      "src": "../../images/img-16x9.png",
      "alt": "A placeholder image with a 16:9 aspect ratio, like a widescreen TV."
    },
    "logo": {
      "src": "../../images/logo-lbg.svg",
      "alt": "A test image for a logo with an arbitrary aspect ratio."
    }
  }
}
